tasi/__init__.py
tasi/_version.py
tasi/base.py
tasi/calculus.py
tasi/dataset/__init__.py
tasi/dataset/base.py
tasi/dataset/geo.py
tasi/dlr/__init__.py
tasi/dlr/dataset.py
tasi/dlr/plotting.py
tasi/extensions/__init__.py
tasi/extensions/base.py
tasi/extensions/smos/__init__.py
tasi/extensions/smos/base.py
tasi/extensions/smos/pet.py
tasi/indexing.py
tasi/io/__init__.py
tasi/io/base/traffic_light.py
tasi/io/geo.py
tasi/io/orm/__init__.py
tasi/io/orm/base.py
tasi/io/orm/db.py
tasi/io/orm/geo.py
tasi/io/orm/pose/__init__.py
tasi/io/orm/pose/base.py
tasi/io/orm/pose/core.py
tasi/io/orm/pose/geo.py
tasi/io/orm/traffic_light.py
tasi/io/orm/traffic_participant.py
tasi/io/orm/trajectory/__init__.py
tasi/io/orm/trajectory/base.py
tasi/io/orm/trajectory/core.py
tasi/io/orm/trajectory/geo.py
tasi/io/orm/utils.py
tasi/io/public/__init__.py
tasi/io/public/base.py
tasi/io/public/geo.py
tasi/io/public/pose/__init__.py
tasi/io/public/pose/base.py
tasi/io/public/pose/core.py
tasi/io/public/pose/geo.py
tasi/io/public/traffic_light.py
tasi/io/public/traffic_participant.py
tasi/io/public/trajectory/__int__.py
tasi/io/public/trajectory/base.py
tasi/io/public/trajectory/core.py
tasi/io/public/trajectory/geo.py
tasi/io/public/trajectory/trajectory.py
tasi/io/util.py
tasi/io/zenodo.py
tasi/logging.py
tasi/plotting/__init__.py
tasi/plotting/plot.py
tasi/plotting/wms.py
tasi/pose/__init__.py
tasi/pose/base.py
tasi/pose/geo.py
tasi/smos/__init__.py
tasi/smos/base.py
tasi/smos/pet.py
tasi/tests/__init__.py
tasi/tests/data/DLR-Highway-Traffic-dataset_v1-1-0.zip
tasi/tests/data/DLR-Urban-Traffic-dataset_v1-2-0.zip
tasi/tests/data/README.md
tasi/tests/dlr/__init__.py
tasi/tests/dlr/test_conversion.py
tasi/tests/dlr/test_filtering.py
tasi/tests/dlr/test_loader.py
tasi/tests/io/__init__.py
tasi/tests/io/test_orm/__init__.py
tasi/tests/io/test_orm/test_pose.py
tasi/tests/io/test_orm/test_trajectory.py
tasi/tests/io/test_public/__init__.py
tasi/tests/io/test_public/test_base.py
tasi-0.13.0.dist-info/METADATA
tasi-0.13.0.dist-info/WHEEL
tasi-0.13.0.dist-info/entry_points.txt
tasi-0.13.0.dist-info/licenses/LICENSE
tasi-0.13.0.dist-info/RECORD
